ac_infinity_ble/__init__.py
ac_infinity_ble/const.py
ac_infinity_ble/device.py
ac_infinity_ble/exceptions.py
ac_infinity_ble/models.py
ac_infinity_ble/protocol.py
ac_infinity_ble/py.typed
ac_infinity_ble/util.py
ac_infinity_ble-0.4.3.dist-info/LICENSE
ac_infinity_ble-0.4.3.dist-info/METADATA
ac_infinity_ble-0.4.3.dist-info/WHEEL
ac_infinity_ble-0.4.3.dist-info/RECORD
