Metadata-Version: 2.1
Name: ac-infinity-ble
Version: 0.4.3
Summary: AC Infinity BLE Controller
Home-page: https://github.com/hunterjm/ac-infinity-ble
License: MIT
Author: Jason Hunter
Author-email: hunterjm@gmail.com
Requires-Python: >=3.10,<4.0
Classifier: Development Status :: 2 - Pre-Alpha
Classifier: Intended Audience :: Developers
Classifier: License :: OSI Approved :: MIT License
Classifier: Natural Language :: English
Classifier: Operating System :: OS Independent
Classifier: Programming Language :: Python :: 3
Classifier: Programming Language :: Python :: 3.10
Classifier: Programming Language :: Python :: 3.11
Classifier: Topic :: Software Development :: Libraries
Requires-Dist: bleak (>=0.20.2)
Requires-Dist: bleak-retry-connector (>=3.0.2)
Project-URL: Bug Tracker, https://github.com/hunterjm/ac-infinity-ble/issues
Project-URL: Changelog, https://github.com/hunterjm/ac-infinity-ble/blob/main/CHANGELOG.md
Project-URL: Documentation, https://ac-infinity-ble.readthedocs.io
Project-URL: Repository, https://github.com/hunterjm/ac-infinity-ble
